odoo/addons/stock_move_assign_picking_hook/README.rst
odoo/addons/stock_move_assign_picking_hook/__init__.py
odoo/addons/stock_move_assign_picking_hook/__manifest__.py
odoo/addons/stock_move_assign_picking_hook/i18n/stock_move_assign_picking_hook.pot
odoo/addons/stock_move_assign_picking_hook/models/__init__.py
odoo/addons/stock_move_assign_picking_hook/models/stock_move.py
odoo/addons/stock_move_assign_picking_hook/readme/CONTRIBUTORS.rst
odoo/addons/stock_move_assign_picking_hook/readme/CREDITS.rst
odoo/addons/stock_move_assign_picking_hook/readme/DESCRIPTION.rst
odoo/addons/stock_move_assign_picking_hook/readme/USAGE.rst
odoo/addons/stock_move_assign_picking_hook/static/description/icon.png
odoo/addons/stock_move_assign_picking_hook/static/description/index.html
odoo14_addon_stock_move_assign_picking_hook-14.0.1.1.2.dist-info/METADATA
odoo14_addon_stock_move_assign_picking_hook-14.0.1.1.2.dist-info/WHEEL
odoo14_addon_stock_move_assign_picking_hook-14.0.1.1.2.dist-info/top_level.txt
odoo14_addon_stock_move_assign_picking_hook-14.0.1.1.2.dist-info/RECORD
